commonroad_vehicle_models-3.0.2.data/data/LICENSE.txt
vehiclemodels/__init__.py
vehiclemodels/init_ks.py
vehiclemodels/init_kst.py
vehiclemodels/init_mb.py
vehiclemodels/init_st.py
vehiclemodels/init_std.py
vehiclemodels/parameters_vehicle1.py
vehiclemodels/parameters_vehicle2.py
vehiclemodels/parameters_vehicle3.py
vehiclemodels/parameters_vehicle4.py
vehiclemodels/vehicle_dynamics_ks.py
vehiclemodels/vehicle_dynamics_kst.py
vehiclemodels/vehicle_dynamics_linearized.py
vehiclemodels/vehicle_dynamics_mb.py
vehiclemodels/vehicle_dynamics_st.py
vehiclemodels/vehicle_dynamics_std.py
vehiclemodels/vehicle_dynamics_std_old.py
vehiclemodels/vehicle_parameters.py
vehiclemodels/parameters/__init__.py
vehiclemodels/parameters/parameters_tire.yaml
vehiclemodels/parameters/parameters_vehicle1.yaml
vehiclemodels/parameters/parameters_vehicle2.yaml
vehiclemodels/parameters/parameters_vehicle3.yaml
vehiclemodels/parameters/parameters_vehicle4.yaml
vehiclemodels/unit_tests/__init__.py
vehiclemodels/unit_tests/test_derivatives.py
vehiclemodels/unit_tests/test_zeroInitialVelocity.py
vehiclemodels/utils/__init__.py
vehiclemodels/utils/acceleration_constraints.py
vehiclemodels/utils/jerk_dot_constraints.py
vehiclemodels/utils/kappa_dot_dot_constraints.py
vehiclemodels/utils/longitudinal_parameters.py
vehiclemodels/utils/steering_constraints.py
vehiclemodels/utils/steering_parameters.py
vehiclemodels/utils/tireParameters.py
vehiclemodels/utils/tire_model.py
vehiclemodels/utils/trailer_parameters.py
vehiclemodels/utils/unitConversion.py
vehiclemodels/utils/vehicle_dynamics_ks_cog.py
commonroad_vehicle_models-3.0.2.dist-info/LICENSE.txt
commonroad_vehicle_models-3.0.2.dist-info/METADATA
commonroad_vehicle_models-3.0.2.dist-info/WHEEL
commonroad_vehicle_models-3.0.2.dist-info/top_level.txt
commonroad_vehicle_models-3.0.2.dist-info/RECORD
