Metadata-Version: 2.1
Name: commonroad-vehicle-models
Version: 3.0.2
Summary: Implementation of vehicle models with varying abstraction levels ranging from kinematic single track model to a multi-body model.
Home-page: https://commonroad.in.tum.de/
Author: Cyber-Physical Systems Group, Technical University of Munich
Author-email: commonroad@lists.lrz.de
License: BSD
Keywords: autonomous automated vehicles driving motion planning
Platform: UNKNOWN
Classifier: Programming Language :: Python :: 3.7
Classifier: License :: OSI Approved :: BSD License
Classifier: Operating System :: POSIX :: Linux
Classifier: Operating System :: MacOS
Requires-Python: >=3.7
License-File: LICENSE.txt
Requires-Dist: omegaconf (>=2.1.1)
